simple_filters/__init__.py
simple_filters/dummy_filter_strategy.py
simple_filters/filter.py
simple_filters/numpy_filter_strategy.py
simple_filters/polynomial_filter_strategy.py
simple_filters/tracker.py
tests/__init__.py
tests/test_filter.py
tests/test_numpy_filter_strategy.py
tests/test_polynomial_filter_strategy.py
tests/test_single_object_tracking.py
tests/test_tracker.py
simple_filters-0.1.6.dist-info/LICENSE
simple_filters-0.1.6.dist-info/METADATA
simple_filters-0.1.6.dist-info/WHEEL
simple_filters-0.1.6.dist-info/top_level.txt
simple_filters-0.1.6.dist-info/RECORD
