Metadata-Version: 2.1
Name: simple-filters
Version: 0.1.6
Summary: A collection of simple NumPy-based filters and trackers optimized for real-time performance
Home-page: https://github.com/tobias-gp/SimpleFilters.git
Author: Tobias Grosse-Puppendahl
Author-email: tobias@grosse-puppenahl.com
License: Apache License 2.0
Platform: UNKNOWN
Classifier: Programming Language :: Python :: 3
Classifier: Operating System :: OS Independent
Requires-Python: >=3.5
Requires-Dist: numpy
Requires-Dist: scipy (>=0.17.0)
